{
  "symbol": "BRETT",
  "generated_at": "2026-07-06T08:21:49.762164",
  "analysis": {
    "symbol": "BRETT",
    "timeframes": {
      "1d": {
        "symbol": "BRETT",
        "timeframe": "1d",
        "timestamp": "2026-07-06T08:21:49.546795",
        "data_quality": 1.0,
        "indicators": {
          "sma_20": 0.005508449999999955,
          "sma_50": 0.006098860000000011,
          "sma_200": 0.008816850000000044,
          "ema_12": 0.005465833787416931,
          "ema_26": 0.005660085737468738,
          "ema_50": 0.006082631509094057,
          "ichimoku_tenkan_sen": 0.0053105,
          "ichimoku_kijun_sen": 0.0058805,
          "ichimoku_senkou_span_a": 0.006374,
          "ichimoku_senkou_span_b": 0.0080445,
          "supertrend": 0.006818383110086274,
          "supertrend_direction": "-1",
          "rsi_14": 47.04302605777033,
          "rsi_7": 52.89925959584145,
          "macd": -0.00019425195005180664,
          "macd_signal": -0.0002733868302933557,
          "macd_histogram": 7.913488024154905e-05,
          "stoch_k": 73.17699855887277,
          "stoch_d": 66.90906482669942,
          "williams_r": -20.187304890738872,
          "bb_upper": 0.0065518599194254986,
          "bb_middle": 0.005508449999999955,
          "bb_lower": 0.004465040080574411,
          "bb_width": 37.883975326109976,
          "bb_position": 0.5088891238499332,
          "atr": 0.00046196275301484314,
          "atr_percentage": 8.35829117088553,
          "volume_sma": 5527622.499999994,
          "volume_ratio": 0.12843948732027208,
          "vwap": 0.034780243103222204,
          "vwap_distance": -84.10879422666268,
          "obv": -763745361.9253532,
          "mfi": 62.41214097675646,
          "current_price": 0.005527,
          "price_change_24h": -17.752976190476197,
          "price_change_7d": -59.02891030392885
        },
        "signals": [
          "TechnicalSignal(indicator='macd', signal_type='buy', strength=<SignalStrength.MODERATE: 3>, confidence=np.float64(0.0001582697604830981), timeframe='1d', price_target=np.float64(0.00596916), stop_loss=np.float64(0.0053059199999999996), risk_reward_ratio=2.0, reasoning='MACD bullish crossover', timestamp='2026-07-06T08:21:49.549245')",
          "TechnicalSignal(indicator='supertrend', signal_type='sell', strength=<SignalStrength.STRONG: 4>, confidence=0.8, timeframe='1d', price_target=np.float64(0.00486376), stop_loss=np.float64(0.006818383110086274), risk_reward_ratio=3.0, reasoning='SuperTrend bearish', timestamp='2026-07-06T08:21:49.549245')"
        ],
        "trend_analysis": {
          "direction": "TrendDirection.NEUTRAL",
          "strength": 0.04999999999999999,
          "confidence": 0.09999999999999998,
          "key_levels": {
            "sma_20": 0.005508449999999955,
            "sma_50": 0.006098860000000011
          },
          "trend_factors": [
            "SuperTrend bearish",
            "MACD above signal line"
          ]
        },
        "support_resistance": {
          "immediate_support": 0.00476,
          "immediate_resistance": 0.007287,
          "strong_support": 0.004474,
          "strong_resistance": 0.008085,
          "pivot_levels": {
            "pivot_point": 0.005550666666666666,
            "resistance_1": 0.005684333333333333,
            "support_1": 0.005464333333333333,
            "resistance_2": 0.005770666666666666,
            "support_2": 0.005330666666666667
          }
        },
        "volume_analysis": {
          "trend": "decreasing",
          "strength": 1.0,
          "patterns": [
            "Volume decreasing"
          ],
          "volume_price_trend": "bullish_divergence"
        },
        "risk_metrics": {
          "volatility_score": 1.383524706238989,
          "risk_level": "very_high",
          "sharpe_estimate": -0.4977573187907335,
          "max_drawdown_estimate": -94.51658976049221,
          "risk_factors": [
            "High volatility: 138.4%",
            "High ATR: 8.4%"
          ]
        },
        "ai_summary": {
          "recommendation": "HOLD",
          "confidence": 0.5,
          "risk_level": "very_high",
          "trend_direction": "NEUTRAL",
          "trend_strength": 0.04999999999999999,
          "signal_count": {
            "buy": 1,
            "sell": 1,
            "warning": 0
          },
          "key_insights": [
            "24h price change: -17.8%"
          ],
          "action_priority": 8,
          "optimal_entry": {
            "aggressive_entry": 0.005527,
            "conservative_entry": 0.00476,
            "breakout_entry": 0.007287
          },
          "risk_management": {
            "position_size": 0.1,
            "stop_loss": 0.00476,
            "take_profit_1": 0.00596916,
            "take_profit_2": 0.006356049999999999,
            "max_risk_per_trade": 0.02,
            "hold_period_days": 14
          }
        }
      },
      "4h": {
        "symbol": "BRETT",
        "timeframe": "4h",
        "timestamp": "2026-07-06T08:21:49.549648",
        "data_quality": 1.0,
        "indicators": {
          "sma_20": 0.005535049999999986,
          "sma_50": 0.005373499999999996,
          "sma_200": 0.005674279999999997,
          "ema_12": 0.005529306388625142,
          "ema_26": 0.005482449581618816,
          "ema_50": 0.005439934790314386,
          "ichimoku_tenkan_sen": 0.005535,
          "ichimoku_kijun_sen": 0.005498,
          "ichimoku_senkou_span_a": 0.00518425,
          "ichimoku_senkou_span_b": 0.005180000000000001,
          "supertrend": 0.005206152466720161,
          "supertrend_direction": "1",
          "rsi_14": 53.694987803025896,
          "rsi_7": 50.029166231423716,
          "macd": 4.685680700632598e-05,
          "macd_signal": 5.739324667169901e-05,
          "macd_histogram": -1.0536439665373026e-05,
          "stoch_k": 50.23084025854098,
          "stoch_d": 53.43182517697741,
          "williams_r": -53.73961218836578,
          "bb_upper": 0.0056907899042111685,
          "bb_middle": 0.005535049999999986,
          "bb_lower": 0.005379310095788803,
          "bb_width": 5.627407311991151,
          "bb_position": 0.47415562812639767,
          "atr": 0.00011718425925730125,
          "atr_percentage": 2.120214569518749,
          "volume_sma": 360246.8499999996,
          "volume_ratio": 0.10053661815502353,
          "vwap": 0.007260068312365755,
          "vwap_distance": -23.871239743211458,
          "obv": -10086888.999999993,
          "mfi": 20.23381441430299,
          "current_price": 0.005527,
          "price_change_24h": 2.011812476928751,
          "price_change_7d": -3.559588204501835
        },
        "signals": [
          "TechnicalSignal(indicator='macd', signal_type='sell', strength=<SignalStrength.MODERATE: 3>, confidence=np.float64(2.1072879330746053e-05), timeframe='4h', price_target=np.float64(0.00508484), stop_loss=np.float64(0.00574808), risk_reward_ratio=2.0, reasoning='MACD bearish crossover', timestamp='2026-07-06T08:21:49.552087')",
          "TechnicalSignal(indicator='supertrend', signal_type='buy', strength=<SignalStrength.STRONG: 4>, confidence=0.8, timeframe='4h', price_target=np.float64(0.0061902400000000005), stop_loss=np.float64(0.005206152466720161), risk_reward_ratio=3.0, reasoning='SuperTrend bullish', timestamp='2026-07-06T08:21:49.552087')"
        ],
        "trend_analysis": {
          "direction": "TrendDirection.NEUTRAL",
          "strength": 0.04999999999999999,
          "confidence": 0.09999999999999998,
          "key_levels": {
            "sma_20": 0.005535049999999986,
            "sma_50": 0.005373499999999996
          },
          "trend_factors": [
            "SuperTrend bullish",
            "MACD below signal line"
          ]
        },
        "support_resistance": {
          "immediate_support": 0.00536,
          "immediate_resistance": 0.005721,
          "strong_support": 0.0049,
          "strong_resistance": 0.005721,
          "pivot_levels": {
            "pivot_point": 0.005530666666666666,
            "resistance_1": 0.005581333333333333,
            "support_1": 0.005483333333333333,
            "resistance_2": 0.005628666666666666,
            "support_2": 0.005432666666666666
          }
        },
        "volume_analysis": {
          "trend": "decreasing",
          "strength": 1.0,
          "patterns": [
            "Volume decreasing"
          ],
          "volume_price_trend": "bearish_divergence"
        },
        "risk_metrics": {
          "volatility_score": 0.42004002505584104,
          "risk_level": "medium",
          "sharpe_estimate": -0.24492961780412192,
          "max_drawdown_estimate": -54.81386392811301,
          "risk_factors": []
        },
        "ai_summary": {
          "recommendation": "HOLD",
          "confidence": 0.5,
          "risk_level": "medium",
          "trend_direction": "NEUTRAL",
          "trend_strength": 0.04999999999999999,
          "signal_count": {
            "buy": 1,
            "sell": 1,
            "warning": 0
          },
          "key_insights": [],
          "action_priority": 6,
          "optimal_entry": {
            "aggressive_entry": 0.005527,
            "conservative_entry": 0.00536,
            "breakout_entry": 0.005721
          },
          "risk_management": {
            "position_size": 0.1,
            "stop_loss": 0.00536,
            "take_profit_1": 0.00596916,
            "take_profit_2": 0.006356049999999999,
            "max_risk_per_trade": 0.02,
            "hold_period_days": 14
          }
        }
      },
      "1h": {
        "symbol": "BRETT",
        "timeframe": "1h",
        "timestamp": "2026-07-06T08:21:49.555056",
        "data_quality": 0.0,
        "indicators": {},
        "signals": [],
        "trend_analysis": {
          "direction": "TrendDirection.NEUTRAL",
          "strength": 0,
          "confidence": 0
        },
        "support_resistance": {},
        "volume_analysis": {},
        "risk_metrics": {
          "risk_level": "unknown"
        },
        "ai_summary": {
          "recommendation": "HOLD",
          "confidence": 0,
          "risk_level": "unknown"
        }
      }
    },
    "summary": {
      "status": "analyzed",
      "data_quality": 1.0,
      "signal_count": 2,
      "recommendation": "HOLD",
      "confidence": 0.5,
      "risk_level": "very_high",
      "trend_direction": "NEUTRAL",
      "key_insights": [
        "24h price change: -17.8%"
      ]
    },
    "last_updated": "2026-07-06T08:21:49.546668"
  },
  "ai_recommendation": {
    "symbol": "BRETT",
    "action": "sell",
    "confidence": 1.0,
    "urgency": 9,
    "target_allocation": 0,
    "expected_roi": 0.05,
    "reasoning": [
      "Sell supertrend: SuperTrend bearish",
      "Strong supertrend: SuperTrend bullish",
      "Stop loss triggered: -59.0% weekly loss"
    ],
    "risk_level": "moderate"
  }
}