{
  "symbol": "ETH",
  "generated_at": "2025-11-26T01:40:21.736206",
  "analysis": {
    "symbol": "ETH",
    "timeframes": {
      "1d": {
        "symbol": "ETH",
        "timeframe": "1d",
        "timestamp": "2025-11-26T01:40:21.343696",
        "data_quality": 1.0,
        "indicators": {
          "sma_20": 3133.4259999999986,
          "sma_50": 3597.391599999997,
          "sma_200": 3513.162949999998,
          "ema_12": 2996.6401876221557,
          "ema_26": 3214.1678939536037,
          "ema_50": 3484.143091266419,
          "ichimoku_tenkan_sen": 2896.745,
          "ichimoku_kijun_sen": 3270.7349999999997,
          "ichimoku_senkou_span_a": 4017.0150000000003,
          "ichimoku_senkou_span_b": 4073.385,
          "supertrend": 2397.412684315939,
          "supertrend_direction": "1",
          "rsi_14": 38.48086476442736,
          "rsi_7": 45.30066069574636,
          "macd": -217.52770633144792,
          "macd_signal": -231.12903272736884,
          "macd_histogram": 13.601326395920921,
          "stoch_k": 34.718715909898414,
          "stoch_d": 28.018746084447656,
          "williams_r": -62.92025061059783,
          "bb_upper": 3788.4223673261467,
          "bb_middle": 3133.4259999999986,
          "bb_lower": 2478.4296326738504,
          "bb_width": 41.80704234445929,
          "bb_position": 0.3772695483363331,
          "atr": 199.14247107161503,
          "atr_percentage": 6.699156344393556,
          "volume_sma": 162073.71033598244,
          "volume_ratio": 0.03581440865250131,
          "vwap": 3167.3056005765293,
          "vwap_distance": -6.145778940342763,
          "obv": -3281116.2918885387,
          "mfi": 30.223295516255632,
          "current_price": 2972.65,
          "price_change_24h": -17.51322912822334,
          "price_change_7d": 12.480655060333515
        },
        "signals": [
          "TechnicalSignal(indicator='macd', signal_type='buy', strength=<SignalStrength.STRONG: 4>, confidence=1.0, timeframe='1d', price_target=np.float64(3210.4620000000004), stop_loss=np.float64(2853.744), risk_reward_ratio=2.0, reasoning='MACD bullish crossover', timestamp='2025-11-26T01:40:21.346574')",
          "TechnicalSignal(indicator='supertrend', signal_type='buy', strength=<SignalStrength.STRONG: 4>, confidence=0.8, timeframe='1d', price_target=np.float64(3329.3680000000004), stop_loss=np.float64(2397.412684315939), risk_reward_ratio=3.0, reasoning='SuperTrend bullish', timestamp='2025-11-26T01:40:21.346574')"
        ],
        "trend_analysis": {
          "direction": "TrendDirection.NEUTRAL",
          "strength": 0.15000000000000002,
          "confidence": 0.30000000000000004,
          "key_levels": {
            "sma_20": 3133.4259999999986,
            "sma_50": 3597.391599999997
          },
          "trend_factors": [
            "Price below both MA20 and MA50",
            "SuperTrend bullish",
            "MACD above signal line"
          ]
        },
        "support_resistance": {
          "immediate_support": 2623.47,
          "immediate_resistance": 3658.8,
          "strong_support": 2623.47,
          "strong_resistance": 4558.9,
          "pivot_levels": {
            "pivot_point": 2932.463333333333,
            "resistance_1": 3007.5366666666664,
            "support_1": 2884.6966666666663,
            "resistance_2": 3055.3033333333333,
            "support_2": 2809.623333333333
          }
        },
        "volume_analysis": {
          "trend": "decreasing",
          "strength": 0.8652612990837865,
          "patterns": [
            "Volume decreasing"
          ],
          "volume_price_trend": "bearish_divergence"
        },
        "risk_metrics": {
          "volatility_score": 0.7335729129997978,
          "risk_level": "medium",
          "sharpe_estimate": 0.20496683156129256,
          "max_drawdown_estimate": -63.20550442676793,
          "risk_factors": [
            "High ATR: 6.7%"
          ]
        },
        "ai_summary": {
          "recommendation": "BUY",
          "confidence": 0.6666666666666666,
          "risk_level": "medium",
          "trend_direction": "NEUTRAL",
          "trend_strength": 0.15000000000000002,
          "signal_count": {
            "buy": 2,
            "sell": 0,
            "warning": 0
          },
          "key_insights": [
            "24h price change: -17.5%"
          ],
          "action_priority": 7,
          "optimal_entry": {
            "aggressive_entry": 2972.65,
            "conservative_entry": 2623.47,
            "breakout_entry": 3658.8
          },
          "risk_management": {
            "position_size": 0.1,
            "stop_loss": 2623.47,
            "take_profit_1": 3210.4620000000004,
            "take_profit_2": 3418.5474999999997,
            "max_risk_per_trade": 0.02,
            "hold_period_days": 14
          }
        }
      },
      "4h": {
        "symbol": "ETH",
        "timeframe": "4h",
        "timestamp": "2025-11-26T01:40:21.346959",
        "data_quality": 1.0,
        "indicators": {
          "sma_20": 2868.5139999999997,
          "sma_50": 2898.4813999999988,
          "sma_200": 3435.354899999999,
          "ema_12": 2907.746630468147,
          "ema_26": 2886.994177296896,
          "ema_50": 2932.9903849422267,
          "ichimoku_tenkan_sen": 2914.52,
          "ichimoku_kijun_sen": 2845.215,
          "ichimoku_senkou_span_a": 2877.0,
          "ichimoku_senkou_span_b": 3094.3199999999997,
          "supertrend": 3154.498694637129,
          "supertrend_direction": "-1",
          "rsi_14": 61.17857554821051,
          "rsi_7": 71.94123886907327,
          "macd": 20.75245317125109,
          "macd_signal": 3.29852804936783,
          "macd_histogram": 17.45392512188326,
          "stoch_k": 84.56648868548176,
          "stoch_d": 73.44839792006297,
          "williams_r": -6.048369004352324,
          "bb_upper": 3026.401154155506,
          "bb_middle": 2868.5139999999997,
          "bb_lower": 2710.6268458444933,
          "bb_width": 11.008288901884832,
          "bb_position": 0.8297798372419669,
          "atr": 67.96616453261869,
          "atr_percentage": 2.2863830095241178,
          "volume_sma": 18066.52684216651,
          "volume_ratio": 0.3212888755271085,
          "vwap": 3862.693117169362,
          "vwap_distance": -23.042035444472443,
          "obv": -1033248.4577210698,
          "mfi": 70.26868483903132,
          "current_price": 2972.65,
          "price_change_24h": 7.853203686234682,
          "price_change_7d": -26.137634237609888
        },
        "signals": [
          "TechnicalSignal(indicator='macd', signal_type='buy', strength=<SignalStrength.STRONG: 4>, confidence=1.0, timeframe='4h', price_target=np.float64(3210.4620000000004), stop_loss=np.float64(2853.744), risk_reward_ratio=2.0, reasoning='MACD bullish crossover', timestamp='2025-11-26T01:40:21.349836')",
          "TechnicalSignal(indicator='supertrend', signal_type='sell', strength=<SignalStrength.STRONG: 4>, confidence=0.8, timeframe='4h', price_target=np.float64(2615.9320000000002), stop_loss=np.float64(3154.498694637129), risk_reward_ratio=3.0, reasoning='SuperTrend bearish', timestamp='2025-11-26T01:40:21.349836')"
        ],
        "trend_analysis": {
          "direction": "TrendDirection.NEUTRAL",
          "strength": 0.04999999999999999,
          "confidence": 0.09999999999999998,
          "key_levels": {
            "sma_20": 2868.5139999999997,
            "sma_50": 2898.4813999999988
          },
          "trend_factors": [
            "SuperTrend bearish",
            "MACD above signal line"
          ]
        },
        "support_resistance": {
          "immediate_support": 2733.83,
          "immediate_resistance": 2986.13,
          "strong_support": 2623.47,
          "strong_resistance": 3170.02,
          "pivot_levels": {
            "pivot_point": 2949.0933333333337,
            "resistance_1": 2990.906666666667,
            "support_1": 2917.9566666666674,
            "resistance_2": 3022.0433333333335,
            "support_2": 2876.143333333334
          }
        },
        "volume_analysis": {
          "trend": "decreasing",
          "strength": 0.45414229777746695,
          "patterns": [
            "Volume decreasing"
          ],
          "volume_price_trend": "bullish_divergence"
        },
        "risk_metrics": {
          "volatility_score": 0.2711816548969411,
          "risk_level": "medium",
          "sharpe_estimate": -0.951515890077487,
          "max_drawdown_estimate": -43.479083575292584,
          "risk_factors": []
        },
        "ai_summary": {
          "recommendation": "HOLD",
          "confidence": 0.5,
          "risk_level": "medium",
          "trend_direction": "NEUTRAL",
          "trend_strength": 0.04999999999999999,
          "signal_count": {
            "buy": 1,
            "sell": 1,
            "warning": 0
          },
          "key_insights": [],
          "action_priority": 7,
          "optimal_entry": {
            "aggressive_entry": 2972.65,
            "conservative_entry": 2733.83,
            "breakout_entry": 2986.13
          },
          "risk_management": {
            "position_size": 0.1,
            "stop_loss": 2836.7176709347627,
            "take_profit_1": 3210.4620000000004,
            "take_profit_2": 3418.5474999999997,
            "max_risk_per_trade": 0.02,
            "hold_period_days": 14
          }
        }
      },
      "1h": {
        "symbol": "ETH",
        "timeframe": "1h",
        "timestamp": "2025-11-26T01:40:21.350204",
        "data_quality": 1.0,
        "indicators": {
          "sma_20": 2921.0594999999976,
          "sma_50": 2894.878399999999,
          "sma_200": 2900.98665,
          "ema_12": 2941.3790211952273,
          "ema_26": 2923.9611747376393,
          "ema_50": 2899.778145266452,
          "ichimoku_tenkan_sen": 2926.115,
          "ichimoku_kijun_sen": 2918.81,
          "ichimoku_senkou_span_a": 2886.9825,
          "ichimoku_senkou_span_b": 2859.98,
          "supertrend": 2853.4750882658877,
          "supertrend_direction": "1",
          "rsi_14": 62.33110395255183,
          "rsi_7": 68.74352025641868,
          "macd": 17.417846457587984,
          "macd_signal": 13.295182031748434,
          "macd_histogram": 4.122664425839551,
          "stoch_k": 85.45804840985572,
          "stoch_d": 84.87040958720506,
          "williams_r": -5.926408336047046,
          "bb_upper": 2992.9165453430446,
          "bb_middle": 2921.0594999999976,
          "bb_lower": 2849.2024546569505,
          "bb_width": 4.91993027482303,
          "bb_position": 0.8610675874041015,
          "atr": 35.046994787112304,
          "atr_percentage": 1.17886257041364,
          "volume_sma": 4150.9212979125,
          "volume_ratio": 0.5677419463927589,
          "vwap": 3217.674728585905,
          "vwap_distance": -7.605639140953698,
          "obv": -215440.77012935036,
          "mfi": 61.867630953510044,
          "current_price": 2972.95,
          "price_change_24h": 1.4402505851764413,
          "price_change_7d": -4.530770317658095
        },
        "signals": [
          "TechnicalSignal(indicator='macd', signal_type='buy', strength=<SignalStrength.STRONG: 4>, confidence=1.0, timeframe='1h', price_target=np.float64(3210.786), stop_loss=np.float64(2854.0319999999997), risk_reward_ratio=2.0, reasoning='MACD bullish crossover', timestamp='2025-11-26T01:40:21.353051')",
          "TechnicalSignal(indicator='supertrend', signal_type='buy', strength=<SignalStrength.STRONG: 4>, confidence=0.8, timeframe='1h', price_target=np.float64(3329.704), stop_loss=np.float64(2853.4750882658877), risk_reward_ratio=3.0, reasoning='SuperTrend bullish', timestamp='2025-11-26T01:40:21.353051')"
        ],
        "trend_analysis": {
          "direction": "TrendDirection.BULLISH",
          "strength": 0.75,
          "confidence": 1.0,
          "key_levels": {
            "sma_20": 2921.0594999999976,
            "sma_50": 2894.878399999999
          },
          "trend_factors": [
            "Price above both MA20 and MA50",
            "SuperTrend bullish",
            "MACD above signal line"
          ]
        },
        "support_resistance": {
          "immediate_support": 2857.39,
          "immediate_resistance": 2980.23,
          "strong_support": 2763.26,
          "strong_resistance": 2986.13,
          "pivot_levels": {
            "pivot_point": 2958.686666666667,
            "resistance_1": 2967.633333333334,
            "support_1": 2945.433333333334,
            "resistance_2": 2980.886666666667,
            "support_2": 2936.4866666666667
          }
        },
        "volume_analysis": {
          "trend": "neutral",
          "strength": 0.5,
          "patterns": [],
          "volume_price_trend": "bullish_confirmation"
        },
        "risk_metrics": {
          "volatility_score": 0.15995341623474335,
          "risk_level": "low",
          "sharpe_estimate": -0.44827367675164054,
          "max_drawdown_estimate": -26.225300737504973,
          "risk_factors": []
        },
        "ai_summary": {
          "recommendation": "BUY",
          "confidence": 0.6666666666666666,
          "risk_level": "low",
          "trend_direction": "BULLISH",
          "trend_strength": 0.75,
          "signal_count": {
            "buy": 2,
            "sell": 0,
            "warning": 0
          },
          "key_insights": [
            "Strong bullish trend"
          ],
          "action_priority": 7,
          "optimal_entry": {
            "aggressive_entry": 2972.95,
            "conservative_entry": 2857.39,
            "breakout_entry": 2980.23
          },
          "risk_management": {
            "position_size": 0.1,
            "stop_loss": 2902.856010425775,
            "take_profit_1": 3210.786,
            "take_profit_2": 3418.8924999999995,
            "max_risk_per_trade": 0.02,
            "hold_period_days": 14
          }
        }
      }
    },
    "summary": {
      "status": "analyzed",
      "data_quality": 1.0,
      "signal_count": 2,
      "recommendation": "BUY",
      "confidence": 0.6666666666666666,
      "risk_level": "medium",
      "trend_direction": "NEUTRAL",
      "key_insights": [
        "24h price change: -17.5%"
      ]
    },
    "last_updated": "2025-11-26T01:40:21.343574"
  },
  "ai_recommendation": {
    "symbol": "ETH",
    "action": "strong_buy",
    "confidence": 1.0,
    "urgency": 8,
    "target_allocation": 0.15,
    "expected_roi": 0.09322373205044589,
    "reasoning": [
      "Strong macd: MACD bullish crossover",
      "Strong supertrend: SuperTrend bullish",
      "Strong macd: MACD bullish crossover"
    ],
    "risk_level": "conservative"
  }
}