{
  "symbol": "IOTX",
  "generated_at": "2026-05-15T03:34:00.276490",
  "analysis": {
    "symbol": "IOTX",
    "timeframes": {
      "1d": {
        "symbol": "IOTX",
        "timeframe": "1d",
        "timestamp": "2026-05-15T03:34:00.184285",
        "data_quality": 1.0,
        "indicators": {
          "sma_20": 0.00484000000000002,
          "sma_50": 0.0047119999999999775,
          "sma_200": 0.006825800000000008,
          "ema_12": 0.004980379182353268,
          "ema_26": 0.004879419134661704,
          "ema_50": 0.004914365126627071,
          "ichimoku_tenkan_sen": 0.0051199999999999996,
          "ichimoku_kijun_sen": 0.00496,
          "ichimoku_senkou_span_a": 0.004845,
          "ichimoku_senkou_span_b": 0.005355,
          "supertrend": 0.005716608883532313,
          "supertrend_direction": "-1",
          "rsi_14": 52.5093946564135,
          "rsi_7": 47.462353991323006,
          "macd": 0.000100960047691564,
          "macd_signal": 8.006297369025366e-05,
          "macd_histogram": 2.0897074001310342e-05,
          "stoch_k": 50.43209876543212,
          "stoch_d": 65.463898241676,
          "williams_r": -53.33333333333332,
          "bb_upper": 0.0055060468609973625,
          "bb_middle": 0.00484000000000002,
          "bb_lower": 0.004173953139002677,
          "bb_width": 27.522597561873564,
          "bb_position": 0.575069793024953,
          "atr": 0.0002620654194133526,
          "atr_percentage": 5.304968004318879,
          "volume_sma": 2294182.004880003,
          "volume_ratio": 0.04545325718630342,
          "vwap": 0.017893323846703193,
          "vwap_distance": -72.39193767283106,
          "obv": 23374164.859993182,
          "mfi": 84.6263438250209,
          "current_price": 0.00494,
          "price_change_24h": 5.106382978723399,
          "price_change_7d": -44.92753623188406
        },
        "signals": [
          "TechnicalSignal(indicator='macd', signal_type='buy', strength=<SignalStrength.MODERATE: 3>, confidence=np.float64(4.1794148002620684e-05), timeframe='1d', price_target=np.float64(0.0053352), stop_loss=np.float64(0.0047424), risk_reward_ratio=2.0, reasoning='MACD bullish crossover', timestamp='2026-05-15T03:34:00.187101')",
          "TechnicalSignal(indicator='supertrend', signal_type='sell', strength=<SignalStrength.STRONG: 4>, confidence=0.8, timeframe='1d', price_target=np.float64(0.0043472), stop_loss=np.float64(0.005716608883532313), risk_reward_ratio=3.0, reasoning='SuperTrend bearish', timestamp='2026-05-15T03:34:00.187101')"
        ],
        "trend_analysis": {
          "direction": "TrendDirection.NEUTRAL",
          "strength": 0.25,
          "confidence": 0.5,
          "key_levels": {
            "sma_20": 0.00484000000000002,
            "sma_50": 0.0047119999999999775
          },
          "trend_factors": [
            "Price above both MA20 and MA50",
            "SuperTrend bearish",
            "MACD above signal line"
          ]
        },
        "support_resistance": {
          "immediate_support": 0.00442,
          "immediate_resistance": 0.0055,
          "strong_support": 0.00436,
          "strong_resistance": 0.0055,
          "pivot_levels": {
            "pivot_point": 0.0049499999999999995,
            "resistance_1": 0.005039999999999999,
            "support_1": 0.004849999999999999,
            "resistance_2": 0.00514,
            "support_2": 0.0047599999999999995
          }
        },
        "volume_analysis": {
          "trend": "neutral",
          "strength": 0.5,
          "patterns": [],
          "volume_price_trend": "bullish_confirmation"
        },
        "risk_metrics": {
          "volatility_score": 0.9057861263738196,
          "risk_level": "high",
          "sharpe_estimate": -1.1990297547798796,
          "max_drawdown_estimate": -89.74477958236659,
          "risk_factors": [
            "High ATR: 5.3%"
          ]
        },
        "ai_summary": {
          "recommendation": "HOLD",
          "confidence": 0.5,
          "risk_level": "high",
          "trend_direction": "NEUTRAL",
          "trend_strength": 0.25,
          "signal_count": {
            "buy": 1,
            "sell": 1,
            "warning": 0
          },
          "key_insights": [],
          "action_priority": 8,
          "optimal_entry": {
            "aggressive_entry": 0.00494,
            "conservative_entry": 0.00442,
            "breakout_entry": 0.0055
          },
          "risk_management": {
            "position_size": 0.1,
            "stop_loss": 0.00442,
            "take_profit_1": 0.0053352,
            "take_profit_2": 0.005680999999999999,
            "max_risk_per_trade": 0.02,
            "hold_period_days": 7
          }
        }
      },
      "4h": {
        "symbol": "IOTX",
        "timeframe": "4h",
        "timestamp": "2026-05-15T03:34:00.187498",
        "data_quality": 1.0,
        "indicators": {
          "sma_20": 0.005123000000000002,
          "sma_50": 0.005059399999999996,
          "sma_200": 0.004756900000000004,
          "ema_12": 0.005019295677249159,
          "ema_26": 0.0050668227425973884,
          "ema_50": 0.0050233021013799525,
          "ichimoku_tenkan_sen": 0.005015,
          "ichimoku_kijun_sen": 0.00518,
          "ichimoku_senkou_span_a": 0.00507,
          "ichimoku_senkou_span_b": 0.00489,
          "supertrend": 0.005255370022670801,
          "supertrend_direction": "-1",
          "rsi_14": 42.475179539935844,
          "rsi_7": 37.531438665004664,
          "macd": -4.7527065348229765e-05,
          "macd_signal": -1.3077456829108701e-05,
          "macd_histogram": -3.444960851912106e-05,
          "stoch_k": 16.145833333333382,
          "stoch_d": 16.840277777777825,
          "williams_r": -87.49999999999996,
          "bb_upper": 0.005559048343529403,
          "bb_middle": 0.005123000000000002,
          "bb_lower": 0.0046869516564706,
          "bb_width": 17.023163909014308,
          "bb_position": 0.2901608815678685,
          "atr": 0.00011087805158628444,
          "atr_percentage": 2.2444949713822764,
          "volume_sma": 354021.9844049992,
          "volume_ratio": 0.29455245519641654,
          "vwap": 0.005075606569483382,
          "vwap_distance": -2.671731302002489,
          "obv": 13112939.481600007,
          "mfi": 46.13443726860622,
          "current_price": 0.00494,
          "price_change_24h": -7.317073170731703,
          "price_change_7d": 0.6109979633401149
        },
        "signals": [
          "TechnicalSignal(indicator='macd', signal_type='sell', strength=<SignalStrength.MODERATE: 3>, confidence=np.float64(6.889921703824212e-05), timeframe='4h', price_target=np.float64(0.0045448), stop_loss=np.float64(0.0051376), risk_reward_ratio=2.0, reasoning='MACD bearish crossover', timestamp='2026-05-15T03:34:00.190406')",
          "TechnicalSignal(indicator='supertrend', signal_type='sell', strength=<SignalStrength.STRONG: 4>, confidence=0.8, timeframe='4h', price_target=np.float64(0.0043472), stop_loss=np.float64(0.005255370022670801), risk_reward_ratio=3.0, reasoning='SuperTrend bearish', timestamp='2026-05-15T03:34:00.190406')"
        ],
        "trend_analysis": {
          "direction": "TrendDirection.BEARISH",
          "strength": 0.45,
          "confidence": 0.9,
          "key_levels": {
            "sma_20": 0.005123000000000002,
            "sma_50": 0.005059399999999996
          },
          "trend_factors": [
            "SuperTrend bearish",
            "MACD below signal line"
          ]
        },
        "support_resistance": {
          "immediate_support": 0.00486,
          "immediate_resistance": 0.0055,
          "strong_support": 0.00474,
          "strong_resistance": 0.0055,
          "pivot_levels": {
            "pivot_point": 0.00496,
            "resistance_1": 0.00498,
            "support_1": 0.00492,
            "resistance_2": 0.00502,
            "support_2": 0.0049
          }
        },
        "volume_analysis": {
          "trend": "decreasing",
          "strength": 0.8210107514513492,
          "patterns": [
            "Volume decreasing"
          ],
          "volume_price_trend": "bearish_divergence"
        },
        "risk_metrics": {
          "volatility_score": 0.3670651159916167,
          "risk_level": "medium",
          "sharpe_estimate": 0.004118819212054503,
          "max_drawdown_estimate": -27.363184079601936,
          "risk_factors": []
        },
        "ai_summary": {
          "recommendation": "SELL",
          "confidence": 0.6666666666666666,
          "risk_level": "medium",
          "trend_direction": "BEARISH",
          "trend_strength": 0.45,
          "signal_count": {
            "buy": 0,
            "sell": 2,
            "warning": 0
          },
          "key_insights": [],
          "action_priority": 6,
          "optimal_entry": {
            "aggressive_entry": 0.00494,
            "conservative_entry": 0.00486,
            "breakout_entry": 0.0055
          },
          "risk_management": {
            "position_size": 0.1,
            "stop_loss": 0.00486,
            "take_profit_1": 0.0053352,
            "take_profit_2": 0.005680999999999999,
            "max_risk_per_trade": 0.02,
            "hold_period_days": 14
          }
        }
      },
      "1h": {
        "symbol": "IOTX",
        "timeframe": "1h",
        "timestamp": "2026-05-15T03:34:00.190812",
        "data_quality": 0.958,
        "indicators": {
          "sma_20": 0.004954500000000004,
          "sma_50": 0.005075799999999992,
          "sma_200": 0.005064450000000002,
          "ema_12": 0.004962113312718512,
          "ema_26": 0.004984618615216573,
          "ema_50": 0.005039255874511591,
          "ichimoku_tenkan_sen": 0.0049700000000000005,
          "ichimoku_kijun_sen": 0.004954999999999999,
          "ichimoku_senkou_span_a": 0.005155,
          "ichimoku_senkou_span_b": 0.00524,
          "supertrend": 0.004837303059935902,
          "supertrend_direction": "1",
          "rsi_14": 42.767746418603465,
          "rsi_7": 40.150452316333585,
          "macd": -2.2505302498060376e-05,
          "macd_signal": -2.8143592886320345e-05,
          "macd_histogram": 5.63829038825997e-06,
          "stoch_k": 39.583333333333435,
          "stoch_d": 44.84649122807037,
          "williams_r": -68.7500000000001,
          "bb_upper": 0.005073286351776677,
          "bb_middle": 0.004954500000000004,
          "bb_lower": 0.004835713648223331,
          "bb_width": 4.795089384465552,
          "bb_position": 0.4389660521468613,
          "atr": 3.743596013797807e-05,
          "atr_percentage": 0.7578129582586655,
          "volume_sma": 87760.05549000013,
          "volume_ratio": 0.00041967384585572283,
          "vwap": 0.004896770000949822,
          "vwap_distance": 0.8828268234324443,
          "obv": 2039629.9055000008,
          "mfi": 50.5260662501428,
          "current_price": 0.00494,
          "price_change_24h": 0.20283975659228382,
          "price_change_7d": 0.4065040650406515
        },
        "signals": [
          "TechnicalSignal(indicator='macd', signal_type='buy', strength=<SignalStrength.MODERATE: 3>, confidence=np.float64(1.127658077651994e-05), timeframe='1h', price_target=np.float64(0.0053352), stop_loss=np.float64(0.0047424), risk_reward_ratio=2.0, reasoning='MACD bullish crossover', timestamp='2026-05-15T03:34:00.193782')",
          "TechnicalSignal(indicator='supertrend', signal_type='buy', strength=<SignalStrength.STRONG: 4>, confidence=0.8, timeframe='1h', price_target=np.float64(0.0055328), stop_loss=np.float64(0.004837303059935902), risk_reward_ratio=3.0, reasoning='SuperTrend bullish', timestamp='2026-05-15T03:34:00.193782')"
        ],
        "trend_analysis": {
          "direction": "TrendDirection.NEUTRAL",
          "strength": 0.15000000000000002,
          "confidence": 0.30000000000000004,
          "key_levels": {
            "sma_20": 0.004954500000000004,
            "sma_50": 0.005075799999999992
          },
          "trend_factors": [
            "Price below both MA20 and MA50",
            "SuperTrend bullish",
            "MACD above signal line"
          ]
        },
        "support_resistance": {
          "immediate_support": 0.00486,
          "immediate_resistance": 0.00505,
          "strong_support": 0.00486,
          "strong_resistance": 0.00542,
          "pivot_levels": {
            "pivot_point": 0.0049366666666666665,
            "resistance_1": 0.004963333333333333,
            "support_1": 0.0049233333333333325,
            "resistance_2": 0.0049766666666666666,
            "support_2": 0.004896666666666666
          }
        },
        "volume_analysis": {
          "trend": "neutral",
          "strength": 0.5,
          "patterns": [],
          "volume_price_trend": "bearish_divergence"
        },
        "risk_metrics": {
          "volatility_score": 0.14400342036225328,
          "risk_level": "low",
          "sharpe_estimate": 0.20743299475079893,
          "max_drawdown_estimate": -10.332103321033218,
          "risk_factors": []
        },
        "ai_summary": {
          "recommendation": "BUY",
          "confidence": 0.6666666666666666,
          "risk_level": "low",
          "trend_direction": "NEUTRAL",
          "trend_strength": 0.15000000000000002,
          "signal_count": {
            "buy": 2,
            "sell": 0,
            "warning": 0
          },
          "key_insights": [],
          "action_priority": 6,
          "optimal_entry": {
            "aggressive_entry": 0.00494,
            "conservative_entry": 0.00486,
            "breakout_entry": 0.00505
          },
          "risk_management": {
            "position_size": 0.1,
            "stop_loss": 0.004865128079724044,
            "take_profit_1": 0.0053352,
            "take_profit_2": 0.005680999999999999,
            "max_risk_per_trade": 0.02,
            "hold_period_days": 14
          }
        }
      }
    },
    "summary": {
      "status": "analyzed",
      "data_quality": 1.0,
      "signal_count": 2,
      "recommendation": "HOLD",
      "confidence": 0.5,
      "risk_level": "high",
      "trend_direction": "NEUTRAL",
      "key_insights": []
    },
    "last_updated": "2026-05-15T03:34:00.184158"
  },
  "ai_recommendation": {
    "symbol": "IOTX",
    "action": "sell",
    "confidence": 1.0,
    "urgency": 9,
    "target_allocation": 0,
    "expected_roi": 0.05,
    "reasoning": [
      "Sell supertrend: SuperTrend bearish",
      "Sell supertrend: SuperTrend bearish",
      "Strong supertrend: SuperTrend bullish"
    ],
    "risk_level": "conservative"
  }
}